pyjavaproperties3.py
pyjavaproperties3_test.py
pyjavaproperties3-0.6.dist-info/METADATA
pyjavaproperties3-0.6.dist-info/WHEEL
pyjavaproperties3-0.6.dist-info/top_level.txt
pyjavaproperties3-0.6.dist-info/RECORD
