Metadata-Version: 2.1
Name: pyjavaproperties3
Version: 0.6
Summary: Python 3 replacement for java.util.Properties.
Home-page: http://pypi.python.org/pypi/pyjavaproperties3
Author: Jesse Noller
Author-email: jnoller@gmail.com
License: PSF License
Platform: UNKNOWN
Classifier: Development Status :: 3 - Alpha
Classifier: Intended Audience :: Developers
Classifier: License :: OSI Approved :: Apache Software License
Classifier: Topic :: Software Development :: Libraries
Classifier: Topic :: Software Development :: Libraries :: Python Modules
